setup.py
cdap_auth_client/AbstractAuthenticationClient.py
cdap_auth_client/AccessToken.py
cdap_auth_client/AuthenticationClient.py
cdap_auth_client/BasicAuthenticationClient.py
cdap_auth_client/Credential.py
cdap_auth_client/RestClientUtils.py
cdap_auth_client/__init__.py
cdap_auth_client.egg-info/PKG-INFO
cdap_auth_client.egg-info/SOURCES.txt
cdap_auth_client.egg-info/dependency_links.txt
cdap_auth_client.egg-info/requires.txt
cdap_auth_client.egg-info/top_level.txt