Metadata-Version: 1.0
Name: cdap-auth-client
Version: 1.0.1
Summary: Authentication client for Cask Data Application Platform
Home-page: UNKNOWN
Author: Cask Data
Author-email: cask-dev@googlegroups.com
License: The Apache License, Version 2.0: http://www.apache.org/licenses/LICENSE-2.0
Platform: UNKNOWN
